remoteio/__init__.py
remoteio/remoteio_client.py
remoteio/remoteio_constants.py
remoteio/remoteio_server.py
remoteio-2.1.dist-info/LICENSE
remoteio-2.1.dist-info/METADATA
remoteio-2.1.dist-info/WHEEL
remoteio-2.1.dist-info/top_level.txt
remoteio-2.1.dist-info/RECORD
